{"introduction": "", "text": "In <em>Crime and Punishment</em>, Dostoevsky explores the importance of individuality and moral courage, even in the face of failure. The following sentence mirrors Dostoevsky\u2019s introspective tone, requiring proper punctuation to ensure clarity and coherence. Select the option that adheres to Standard English conventions while preserving the philosophical weight of the statement.", "question": "<em>\"Dostoevsky emphasizes the value of forging one\u2019s own path ______\"</em>", "A": "affirming that individuality and courage outweigh external approval.", "B": "affirming, that individuality and courage outweigh external approval.", "C": "affirming that individuality, and courage outweigh external approval.", "D": "affirming that individuality and courage outweigh; external approval.", "correct": "A", "explanation": "<strong>Correct Answer:</strong> Choice <strong>A</strong> is correct because it provides a logical and fluid connection between ideas without introducing unnecessary punctuation, reflecting Dostoevsky\u2019s reflective and philosophical tone.<strong>Why Others Are Incorrect:</strong><strong>B.</strong> The comma after affirming disrupts the sentence flow and creates an unnecessary pause.<strong>C.</strong> The comma after individuality improperly fragments the sentence, making it awkward and less effective.<strong>D.</strong> The semicolon after courage is inappropriate because the second part of the sentence is not an independent clause, breaking its logical structure."}