{"introduction": "", "text": "In <em>The Scarlet Letter</em>, Hawthorne explores the psychological toll of guilt and the complexity of human relationships when secrecy is involved. The following sentence mirrors Hawthorne\u2019s reflective tone, requiring proper punctuation to maintain clarity and logical flow. Select the option that adheres to Standard English conventions while preserving the layered meaning of the statement.", "question": "<em>\"Hawthorne reveals that secrecy can deepen guilt and distort relationships ______\"</em>", "A": "leading individuals, to deceive even those who seek to help them.", "B": "leading individuals to deceive even those who seek to help them.", "C": "leading individuals to deceive even those, who seek to help them.", "D": "leading individuals; to deceive even those who seek to help them.", "correct": "B", "explanation": "<strong>Correct Answer:</strong> Choice <strong>A</strong> is correct because it provides a smooth and logical connection between ideas without introducing unnecessary punctuation, reflecting Hawthorne\u2019s thoughtful and analytical tone.<strong>Why Others Are Incorrect:</strong><strong>B.</strong> The comma after individuals disrupts the sentence flow, creating an unnecessary pause.<strong>C.</strong> The comma after those improperly fragments the sentence, making it grammatically awkward.<strong>D.</strong> The semicolon after individuals is inappropriate because the second clause is not independent, breaking the sentence\u2019s structure."}