{"introduction": "", "question": "Read the passage below and choose the most appropriate transition word or phrase to fill in the blank.", "text": "In <em>Pride and Prejudice</em>, Jane Austen explores the social expectations of marriage through the character of Elizabeth Bennet, who is intelligent, independent, and not eager to conform to the traditional norms of her time. Elizabeth's initial prejudice against Mr. Darcy is rooted in her belief that he is arrogant and dismissive. _____, as Elizabeth gets to know Mr. Darcy better, she realizes that her initial judgment was flawed and begins to appreciate his true character, which eventually leads to her feelings of love for him.", "A": "Consequently", "B": "Nevertheless", "C": "In contrast", "D": "For example", "correct": "A", "explanation": "Correct choice D: Consequently\nThe correct answer, \"Consequently,\" indicates that Elizabeth\u2019s shift in perception of Mr. Darcy directly leads to her feelings of love for him. It shows a cause-and-effect relationship between her growing understanding of his true character and the resulting emotional change.\nA) For example would incorrectly suggest that Elizabeth\u2019s change of heart is just an illustration, while the passage is focused on a direct result of her changing opinion.\nB) Nevertheless would imply a contradiction, but the passage is showing a development, not an opposition.\nC) In contrast would incorrectly suggest that Elizabeth\u2019s feelings are in direct opposition to something stated earlier, when in fact they are a result of her deeper understanding of Mr. Darcy."}