{"introduction": "", "question": "Read the passage below and choose the most appropriate transition word or phrase to fill in the blank.", "text": "In <em>Of Mice and Men</em>, John Steinbeck explores the struggles of two migrant workers, George and Lennie, during the Great Depression. George dreams of owning a small farm where he and Lennie can live in peace and independence. _____ their aspirations, the harsh realities of economic hardship and societal prejudice ultimately prevent them from achieving their goal.", "A": "Because of", "B": "As a result of", "C": "In contrast to", "D": "Despite", "correct": "D", "explanation": "Correct choice A: Despite\nThe correct answer, \"Despite,\" introduces a contrast between George and Lennie\u2019s hopeful aspirations and the harsh realities that prevent them from fulfilling those dreams. It highlights the gap between their vision of a better life and the challenges they face.\nB) As a result of would imply that their dreams were hindered because of their aspirations, which does not align with the meaning of the sentence.\nC) In contrast to would be tempting but does not fit naturally in this context, as it is used more for comparing two different things than for introducing contrasting outcomes.\nD) Because of incorrectly suggests causality, implying that their aspirations directly caused their failure, which is not what the passage communicates."}