{"introduction": "Excerpt from Jane Eyre by Charlotte Bront\u00eb", "text": "\"Throughout her life, Jane Eyre demonstrates resilience in the face of hardship, from her difficult childhood at Gateshead to her challenges at Lowood School. Her independence and moral strength guide her as she seeks respect and equality in her relationships.\"", "question": "Which line from <em>Jane Eyre</em> best illustrates Jane\u2019s strength and independence?", "A": "\u201cShe looked out at the moors, a vast solitude, and felt at peace.\u201d", "B": "\u201cI am no bird; and no net ensnares me: I am a free human being with an independent will.\u201d", "C": "\u201cMy heart may be weak, but I shall endure whatever I must.\u201d", "D": "\u201cI have served others all my life, but now I must find my own path.\u201d", "correct": "B", "explanation": "Choice A is correct as it directly conveys Jane\u2019s declaration of independence and inner strength, showing her resolve to be her own person.\nChoice B is incorrect, as it suggests endurance but lacks emphasis on independence.\nChoice C is misleading, reflecting peace but not strength.\nChoice D is incorrect, focusing on self-discovery rather than outright independence."}