{"introduction": "", "text": "In <em>The Tipping Point: How Little Things Can Make a Big Difference</em>, Malcolm Gladwell discusses how small, seemingly insignificant events or actions can trigger larger, widespread changes. He uses the example of the rise of syphilis in Baltimore, which was sparked by a small group of people who spread the disease, resulting in an epidemic. Gladwell argues that social epidemics, like the spread of disease or trends, are often driven by a few individuals who have the power to influence the behavior of others. He emphasizes that these tipping points are crucial in understanding how large-scale changes occur. This idea suggests that ______.", "question": "Which choice most logically completes the text?", "A": "large-scale changes happen suddenly and without any identifiable cause or initial influence.", "B": "social epidemics are always predictable and can be controlled through careful planning.", "C": "small, seemingly insignificant events can have a disproportionate impact and trigger widespread changes.", "D": "tipping points occur only in the spread of diseases and do not apply to other social phenomena.", "correct": "C", "explanation": "<strong>Choice B</strong> is the best answer. Gladwell emphasizes that small events or actions can have a disproportionate impact and lead to large, widespread changes, supporting this conclusion.<strong>Choice A</strong> is incorrect. The passage suggests that tipping points are driven by identifiable causes and influencers, not random or sudden events.<strong>Choice C</strong> is incorrect. While Gladwell discusses tipping points, he does not claim that they are entirely predictable or controllable.<strong>Choice D</strong> is incorrect. The concept of tipping points applies to many social phenomena, not just the spread of diseases, making this statement false.<h3>Question Difficulty: Easy</h3><strong>Assessment</strong>: SAT Reading and Writing<br><strong>Domain</strong>: Information and Ideas<br><strong>Skill</strong>: Inferences"}